inhibitor_tool/__init__.py
inhibitor_tool/auth.py
inhibitor_tool/cli.py
inhibitor_tool/config.py
inhibitor_tool/constants.py
inhibitor_tool/inhibitor.py
inhibitor_tool/utils.py
inhibitor_tool-5.2.1.dist-info/LICENSE
inhibitor_tool-5.2.1.dist-info/METADATA
inhibitor_tool-5.2.1.dist-info/WHEEL
inhibitor_tool-5.2.1.dist-info/entry_points.txt
inhibitor_tool-5.2.1.dist-info/top_level.txt
inhibitor_tool-5.2.1.dist-info/RECORD
