Metadata-Version: 2.1
Name: inhibitor-tool
Version: 5.2.1
Summary: A tool for adding items to the inhibition list via API
Home-page: https://github.com/pwxwmm/inhibitor_tool/tree/feature/v2.0.0
Author: mmwei3
Author-email: mmwei3@iflytek.com
License: UNKNOWN
Platform: UNKNOWN
Classifier: Programming Language :: Python :: 3
Classifier: License :: OSI Approved :: MIT License
Classifier: Operating System :: OS Independent
Requires-Python: >=3.6
License-File: LICENSE
Requires-Dist: requests
